ifeatpro/__init__.py
ifeatpro/features.py
ifeatpro/data/AAidx.txt
ifeatpro/data/Grantham.txt
ifeatpro/data/PAAC.txt
ifeatpro/data/Schneider-Wrede.txt
ifeatpro/data/__init__.py
ifeatpro/data/test_seq.fa
ifeatpro-0.0.3.dist-info/LICENSE
ifeatpro-0.0.3.dist-info/METADATA
ifeatpro-0.0.3.dist-info/WHEEL
ifeatpro-0.0.3.dist-info/top_level.txt
ifeatpro-0.0.3.dist-info/RECORD
