Metadata-Version: 2.1
Name: ifeatpro
Version: 0.0.3
Summary: A python tool for numerically encoding protein sequences based on physicochemical properties
Home-page: https://github.com/deeprob/ifeatpro.git
Author: Deepro Banerjee
Author-email: deepro.2.4@gmail.com
License: UNKNOWN
Platform: UNKNOWN
Classifier: Programming Language :: Python :: 3
Classifier: License :: OSI Approved :: MIT License
Classifier: Operating System :: OS Independent
Requires-Python: >=3.9
License-File: LICENSE
Requires-Dist: numpy
